gaapi4py/__init__.py
gaapi4py/__version__.py
gaapi4py/client.py
gaapi4py-1.2.0.dist-info/LICENCE
gaapi4py-1.2.0.dist-info/METADATA
gaapi4py-1.2.0.dist-info/WHEEL
gaapi4py-1.2.0.dist-info/top_level.txt
gaapi4py-1.2.0.dist-info/RECORD
