Metadata-Version: 2.1
Name: gaapi4py
Version: 1.2.0
Summary: Google Analytics Reporting API v4 for Python 3
Home-page: http://github.com/gaapi4py/gaapi4py
Author: Oleh Omelchenko
Author-email: ptrvtch@gmail.com
License: MIT
Platform: UNKNOWN
Classifier: Programming Language :: Python :: 3
Classifier: Development Status :: 4 - Beta
Classifier: License :: OSI Approved :: MIT License
Classifier: Operating System :: OS Independent
Requires-Dist: pandas
Requires-Dist: oauth2client
Requires-Dist: google-api-python-client
